TracGoogleSitemapPlugin-1.1.dist-info/METADATA
TracGoogleSitemapPlugin-1.1.dist-info/RECORD
TracGoogleSitemapPlugin-1.1.dist-info/WHEEL
TracGoogleSitemapPlugin-1.1.dist-info/entry_points.txt
TracGoogleSitemapPlugin-1.1.dist-info/top_level.txt
tracgooglesitemap/__init__.py
tracgooglesitemap/notify.py
tracgooglesitemap/plugin.py
